[
    {
        "id": "b2bb172812ed38f1",
        "type": "change",
        "z": "9524c921fa84dfa0",
        "name": "LED Change Node",
        "rules": [
            {
                "t": "set",
                "p": "payload",
                "pt": "msg",
                "to": "payload",
                "tot": "msg"
            },
            {
                "t": "set",
                "p": "topic",
                "pt": "msg",
                "to": "toggle-led",
                "tot": "str"
            },
            {
                "t": "set",
                "p": "qos",
                "pt": "msg",
                "to": "1",
                "tot": "str"
            }
        ],
        "action": "",
        "property": "",
        "from": "",
        "to": "",
        "reg": false,
        "x": 530,
        "y": 180,
        "wires": [
            [
                "188514e44ee000fb",
                "2a3f237483bc21e9"
            ]
        ]
    }
]